dhbw/__init__.py
dhbw/dasp/__init__.py
dhbw/dasp/fft.py
dhbw/dasp/filter.py
dhbw/dasp/io.py
dhbw/dasp/math.py
dhbw/dasp/pitch.py
dhbw/dasp/plot.py
dhbw/dasp/signal.py
dhbw/dasp/stft.py
dhbw-1.5.3.dist-info/LICENSE
dhbw-1.5.3.dist-info/METADATA
dhbw-1.5.3.dist-info/WHEEL
dhbw-1.5.3.dist-info/top_level.txt
dhbw-1.5.3.dist-info/RECORD
