Metadata-Version: 2.1
Name: dhbw
Version: 1.5.3
Summary: DHBW lecture accompanying Python package.
Home-page: https://github.com/jurihock/dhbw-python
Author: Juergen Hock
Author-email: juergen.hock@jurihock.de
License: GPL-3.0
Keywords: digital,audio,signal,processing,dasp,dhbw,python
Classifier: Intended Audience :: Education
Classifier: License :: OSI Approved :: GNU General Public License v3 (GPLv3)
Classifier: Programming Language :: Python :: 3
Classifier: Topic :: Education
Classifier: Topic :: Multimedia :: Sound/Audio
Classifier: Topic :: Multimedia :: Sound/Audio :: Analysis
Classifier: Topic :: Multimedia :: Sound/Audio :: Sound Synthesis
Requires-Python: >=3
License-File: LICENSE
Requires-Dist: matplotlib
Requires-Dist: numpy >=1.20.0
Requires-Dist: scipy
